__init__.py
absurdsortlib.py
absurdsortlib-1.0.0.dist-info/licenses/LICENSE.txt
absurdsortlib-1.0.0.dist-info/METADATA
absurdsortlib-1.0.0.dist-info/WHEEL
absurdsortlib-1.0.0.dist-info/top_level.txt
absurdsortlib-1.0.0.dist-info/RECORD
